fran_calculator/__init__.py
fran_calculator/franCalc.py
fran_calculator/modules.py
francalculator-0.6.dist-info/licenses/LICENSE
francalculator-0.6.dist-info/METADATA
francalculator-0.6.dist-info/WHEEL
francalculator-0.6.dist-info/top_level.txt
francalculator-0.6.dist-info/RECORD
