Metadata-Version: 2.4
Name: francalculator
Version: 0.6
Summary: Biblioteca para cálculos matemáticos e engenharia
Author: Lukydnomo
Classifier: Programming Language :: Python :: 3
Classifier: License :: OSI Approved :: MIT License
Classifier: Operating System :: OS Independent
Requires-Python: >=3.6
License-File: LICENSE
Requires-Dist: requests
Requires-Dist: pathlib
Requires-Dist: colorama
Dynamic: author
Dynamic: classifier
Dynamic: license-file
Dynamic: requires-dist
Dynamic: requires-python
Dynamic: summary
